lionz/__init__.py
lionz/constants.py
lionz/file_utilities.py
lionz/image_conversion.py
lionz/image_processing.py
lionz/input_validation.py
lionz/lionz.py
lionz/models.py
lionz/predict.py
lionz/resources.py
lionz/system.py
lionz/nnUNet_custom_trainer/LION_custom_trainers.py
lionz/nnUNet_custom_trainer/__init__.py
lionz/nnUNet_custom_trainer/utility.py
lionz-0.19.6.dist-info/licenses/LICENSE
lionz-0.19.6.dist-info/METADATA
lionz-0.19.6.dist-info/WHEEL
lionz-0.19.6.dist-info/entry_points.txt
lionz-0.19.6.dist-info/top_level.txt
lionz-0.19.6.dist-info/RECORD
