Metadata-Version: 2.4
Name: lionz
Version: 0.19.6
Summary: A toolkit for precise segmentation of tumors in PET/CT scans.
Author-email: Lalith Kumar Shiyam Sundar <lalith.shiyamsundar@meduniwien.ac.at>, Sebastian Gutschmayer <sebastian.gutschmayer@meduniwien.ac.at>, Manuel Pires <manuel.pires@meduniwien.ac.at>
License-Expression: GPL-3.0-only
Project-URL: Homepage, https://github.com/QIMP-Team/lionz
Project-URL: Bug Tracker, https://github.com/QIMP-Team/lionz/issues
Project-URL: Documentation, https://lionz.readthedocs.io/en/latest/
Project-URL: Source, https://github.com/QIMP-Team/lionz
Keywords: lesion segmentation,tumors,PET/CT,medical imaging
Classifier: Programming Language :: Python :: 3
Classifier: Operating System :: OS Independent
Requires-Python: >=3.10
License-File: LICENSE
Requires-Dist: nnunetv2>=2.6.0
Requires-Dist: nibabel
Requires-Dist: halo
Requires-Dist: pandas
Requires-Dist: SimpleITK
Requires-Dist: pydicom~=2.2.2
Requires-Dist: imageio
Requires-Dist: numpy<2.0
Requires-Dist: matplotlib
Requires-Dist: pyfiglet
Requires-Dist: cfonts
Requires-Dist: rich-click
Requires-Dist: natsort
Requires-Dist: pillow
Requires-Dist: colorama
Requires-Dist: dask
Requires-Dist: rich
Requires-Dist: dicom2nifti~=2.4.8
Requires-Dist: emoji
Requires-Dist: dask[distributed]
Requires-Dist: opencv-python
Dynamic: license-file
